.DS_Store
generalized_blender/__init__.py
generalized_blender/generalized_blender.py
generalized_blender-0.0.0.dist-info/DESCRIPTION.rst
generalized_blender-0.0.0.dist-info/METADATA
generalized_blender-0.0.0.dist-info/RECORD
generalized_blender-0.0.0.dist-info/WHEEL
generalized_blender-0.0.0.dist-info/metadata.json
generalized_blender-0.0.0.dist-info/top_level.txt
