Metadata-Version: 2.0
Name: generalized-blender
Version: 0.0.0
Summary: Python implementation of generalized model blender with K fold CV
Home-page: https://github.com/Pradeep3490/Blender_Package
Author: Pradeep Jeyachandran
Author-email: charmofsilence@gmail.com
License: UNKNOWN
Platform: UNKNOWN
Requires-Dist: numpy
Requires-Dist: scikit-learn
Requires-Dist: scipy
